proto/__init__.py
proto/event_pb2.py
ebook_searching_proto-0.1.3.dist-info/METADATA
ebook_searching_proto-0.1.3.dist-info/WHEEL
ebook_searching_proto-0.1.3.dist-info/top_level.txt
ebook_searching_proto-0.1.3.dist-info/RECORD
